odoo/addons/crm_sale_marketing/README.rst
odoo/addons/crm_sale_marketing/__init__.py
odoo/addons/crm_sale_marketing/__manifest__.py
odoo/addons/crm_sale_marketing/i18n/crm_sale_marketing.pot
odoo/addons/crm_sale_marketing/i18n/de.po
odoo/addons/crm_sale_marketing/static/description/icon.png
odoo/addons/crm_sale_marketing/views/crm_sale_marketing.xml
odoo11_addon_crm_sale_marketing-11.0.1.0.0.99.dev2.dist-info/METADATA
odoo11_addon_crm_sale_marketing-11.0.1.0.0.99.dev2.dist-info/RECORD
odoo11_addon_crm_sale_marketing-11.0.1.0.0.99.dev2.dist-info/WHEEL
odoo11_addon_crm_sale_marketing-11.0.1.0.0.99.dev2.dist-info/top_level.txt
